MANIFEST.in
NEWS.txt
README.rst
setup.py
src/cypher/__init__.py
src/cypher/column_guesser.py
src/cypher/connection.py
src/cypher/magic.py
src/cypher/parse.py
src/cypher/run.py
src/cypher/utils.py
src/ipython_cypher.egg-info/PKG-INFO
src/ipython_cypher.egg-info/SOURCES.txt
src/ipython_cypher.egg-info/dependency_links.txt
src/ipython_cypher.egg-info/not-zip-safe
src/ipython_cypher.egg-info/requires.txt
src/ipython_cypher.egg-info/top_level.txt