Metadata-Version: 1.1
Name: ipython-cypher
Version: 0.2.1
Summary: Neo4j Cypher cell and line magic for IPython, Pandas, NetworkX and matplotlib
Home-page: https://github.com/versae/ipython-cypher
Author: Javier de la Rosa
Author-email: versae@gmail.com
License: GPL
Keywords: ipython neo4j cypher pandas networkx neo4jrestclient
Platform: UNKNOWN
Classifier: Development Status :: 3 - Alpha
Classifier: Environment :: Console
Classifier: License :: OSI Approved :: GNU General Public License (GPL)
Classifier: Topic :: Database
Classifier: Topic :: Database :: Front-Ends
Classifier: Programming Language :: Python :: 3
Classifier: Programming Language :: Python :: 2
